flask_ctx/__init__.py
flask_ctx/context_processors.py
flask_ctx-1.0.0.dist-info/DESCRIPTION.rst
flask_ctx-1.0.0.dist-info/LICENSE.txt
flask_ctx-1.0.0.dist-info/METADATA
flask_ctx-1.0.0.dist-info/RECORD
flask_ctx-1.0.0.dist-info/WHEEL
flask_ctx-1.0.0.dist-info/metadata.json
flask_ctx-1.0.0.dist-info/top_level.txt
