Metadata-Version: 2.0
Name: flask-ctx
Version: 1.0.0
Summary: A simple integration of the CTX defense against side-channel attacks for Flask projects.
Home-page: https://github.com/dimkarakostas/ctx
Author: Dimitris Karakostas
Author-email: dimit.karakostas@gmail.com
License: MIT
Download-URL: https://github.com/dimkarakostas/ctx
Keywords: flask ctx defense compression security BREACH
Platform: UNKNOWN
Classifier: Environment :: Web Environment
Classifier: Framework :: Flask
Classifier: Intended Audience :: Developers
Classifier: License :: OSI Approved :: MIT License
Classifier: Operating System :: OS Independent
Classifier: Programming Language :: Python
Classifier: Programming Language :: Python :: 2
Classifier: Programming Language :: Python :: 2.7
Classifier: Topic :: Security
Classifier: Topic :: Security :: Cryptography
Requires-Dist: Flask (>=0.10)
Requires-Dist: ctx-defense
